fastgenius/__init__.py
fastgenius/api.py
fastgenius/asynchronous.py
fastgenius/cache.py
fastgenius/genius.py
fastgenius/parser.py
fastgenius/requester.py
fastgenius/utils.py
fastgenius/public_methods/__init__.py
fastgenius/public_methods/album.py
fastgenius/public_methods/annotation.py
fastgenius/public_methods/article.py
fastgenius/public_methods/artist.py
fastgenius/public_methods/cover_art.py
fastgenius/public_methods/discussion.py
fastgenius/public_methods/leaderboard.py
fastgenius/public_methods/misc.py
fastgenius/public_methods/question.py
fastgenius/public_methods/referent.py
fastgenius/public_methods/search.py
fastgenius/public_methods/song.py
fastgenius/public_methods/user.py
fastgenius/public_methods/video.py
fastgenius/types/__init__.py
fastgenius/types/artist.py
fastgenius/types/disk_list.py
fastgenius/types/song.py
fastgenius-0.0.3.dist-info/LICENSE
fastgenius-0.0.3.dist-info/METADATA
fastgenius-0.0.3.dist-info/WHEEL
fastgenius-0.0.3.dist-info/top_level.txt
fastgenius-0.0.3.dist-info/RECORD
