Metadata-Version: 2.1
Name: fastgenius
Version: 0.0.3
Summary: A Python wrapper around the Genius API for large scale applications
Home-page: https://github.com/theomart/fastgenius
Author: Theo Martin
Author-email: contacttheomartin+fastgenius@gmail.com
License: GNU GPLv3
Keywords: genius api genius-api music lyrics artists songs fast async python wrapper
Platform: UNKNOWN
Classifier: Topic :: Software Development :: Libraries
Classifier: License :: OSI Approved :: MIT License
Classifier: Operating System :: OS Independent
Classifier: Programming Language :: Python
Classifier: Programming Language :: Python :: 3
Requires-Dist: beautifulsoup4 (>=4.6.0)
Requires-Dist: aiohttp
Requires-Dist: tqdm
Requires-Dist: pickledb
Requires-Dist: nest-asyncio
Requires-Dist: unidecode
Requires-Dist: lxml
Provides-Extra: dev
Requires-Dist: sphinx (~=3.2) ; extra == 'dev'
Requires-Dist: sphinx-rtd-theme ; extra == 'dev'
Provides-Extra: docs
Requires-Dist: sphinx (~=3.2) ; extra == 'docs'
Requires-Dist: sphinx-rtd-theme ; extra == 'docs'
